{
  "session_id": "20260714_031854_c2a49e",
  "message_id": 9432,
  "call_index": 2,
  "tool_name": "terminal",
  "call": {
    "id": "call_GtgRTp9QLDwwAsNum2bm6Boq",
    "call_id": "call_GtgRTp9QLDwwAsNum2bm6Boq",
    "response_item_id": "fc_071f367ba0e10612016a552ac0f6508191a7b238c08e5180a0",
    "type": "function",
    "function": {
      "name": "terminal",
      "arguments": "{\"command\":\"test -f 'C:/Users/theai/AppData/Local/hermes/profiles/d-drive-profile/state.db' && printf 'state_db_exists\\\\n' || printf 'state_db_missing\\\\n'; sqlite3 'C:/Users/theai/AppData/Local/hermes/profiles/d-drive-profile/state.db' '.tables'\",\"timeout\":30,\"workdir\":\"D:/Projects/ToE_21st_June_NEWEST\"}"
    }
  },
  "parsed_arguments": {
    "command": "test -f 'C:/Users/theai/AppData/Local/hermes/profiles/d-drive-profile/state.db' && printf 'state_db_exists\\n' || printf 'state_db_missing\\n'; sqlite3 'C:/Users/theai/AppData/Local/hermes/profiles/d-drive-profile/state.db' '.tables'",
    "timeout": 30,
    "workdir": "D:/Projects/ToE_21st_June_NEWEST"
  }
}
